galaxies_datasets/__init__.py
galaxies_datasets/__main__.py
galaxies_datasets/datasets/__init__.py
galaxies_datasets/datasets/eagle/__init__.py
galaxies_datasets/datasets/eagle/checksums.tsv
galaxies_datasets/datasets/eagle/dummy_data/RecalL0025N0752/27/data.csv
galaxies_datasets/datasets/eagle/dummy_data/RecalL0025N0752/27/images/galedge_1397599.png
galaxies_datasets/datasets/eagle/dummy_data/RecalL0025N0752/27/images/galedge_6774614.png
galaxies_datasets/datasets/eagle/dummy_data/RecalL0025N0752/27/images/galedge_846422.png
galaxies_datasets/datasets/eagle/dummy_data/RecalL0025N0752/27/images/galface_1397599.png
galaxies_datasets/datasets/eagle/dummy_data/RecalL0025N0752/27/images/galface_6774614.png
galaxies_datasets/datasets/eagle/dummy_data/RecalL0025N0752/27/images/galface_846422.png
galaxies_datasets/datasets/eagle/dummy_data/RecalL0025N0752/27/images/galrand_1397599.png
galaxies_datasets/datasets/eagle/dummy_data/RecalL0025N0752/27/images/galrand_6774614.png
galaxies_datasets/datasets/eagle/dummy_data/RecalL0025N0752/27/images/galrand_846422.png
galaxies_datasets/datasets/eagle/dummy_data/RefL0025N0376/27/data.csv
galaxies_datasets/datasets/eagle/dummy_data/RefL0025N0376/27/images/galedge_135108.png
galaxies_datasets/datasets/eagle/dummy_data/RefL0025N0376/27/images/galedge_166339.png
galaxies_datasets/datasets/eagle/dummy_data/RefL0025N0376/27/images/galedge_343558.png
galaxies_datasets/datasets/eagle/dummy_data/RefL0025N0376/27/images/galface_135108.png
galaxies_datasets/datasets/eagle/dummy_data/RefL0025N0376/27/images/galface_166339.png
galaxies_datasets/datasets/eagle/dummy_data/RefL0025N0376/27/images/galface_343558.png
galaxies_datasets/datasets/eagle/dummy_data/RefL0025N0376/27/images/galrand_135108.png
galaxies_datasets/datasets/eagle/dummy_data/RefL0025N0376/27/images/galrand_166339.png
galaxies_datasets/datasets/eagle/dummy_data/RefL0025N0376/27/images/galrand_343558.png
galaxies_datasets/datasets/eagle/dummy_data/RefL0025N0752/27/data.csv
galaxies_datasets-0.1.2.dist-info/entry_points.txt
galaxies_datasets-0.1.2.dist-info/LICENSE.rst
galaxies_datasets-0.1.2.dist-info/WHEEL
galaxies_datasets-0.1.2.dist-info/METADATA
galaxies_datasets-0.1.2.dist-info/RECORD
