Metadata-Version: 2.1
Name: galaxies-datasets
Version: 0.1.2
Summary: Galaxies Datasets
Home-page: https://github.com/lbignone/galaxies_datasets
License: MIT
Author: Lucas Bignone
Author-email: lbignone@gmail.com
Requires-Python: >=3.7.1,<4.0.0
Classifier: Development Status :: 1 - Planning
Classifier: License :: OSI Approved :: MIT License
Classifier: Programming Language :: Python :: 3
Classifier: Programming Language :: Python :: 3.7
Classifier: Programming Language :: Python :: 3.8
Classifier: Programming Language :: Python :: 3.9
Requires-Dist: eagleSqlTools (>=2.0.0,<3.0.0)
Requires-Dist: pandas (>=1.3.2,<2.0.0)
Requires-Dist: tensorflow (>=2.4.0,<3.0.0)
Requires-Dist: tensorflow-datasets (>=4.4.0,<5.0.0)
Requires-Dist: typer (>=0.4.0,<0.5.0)
Project-URL: Changelog, https://github.com/lbignone/galaxies_datasets/releases
Project-URL: Documentation, https://galaxies_datasets.readthedocs.io
Project-URL: Repository, https://github.com/lbignone/galaxies_datasets
